simplesrs/__init__.py
simplesrs/db.py
simplesrs/default.py
simplesrs-0.1.1.2.dist-info/LICENSE
simplesrs-0.1.1.2.dist-info/WHEEL
simplesrs-0.1.1.2.dist-info/METADATA
simplesrs-0.1.1.2.dist-info/RECORD
