Metadata-Version: 2.1
Name: simplesrs
Version: 0.1.1.2
Summary: Simple SRS (spaced-recognition system) mechanism and database
Home-page: https://github.com/patarapolw/simplesrs
License: UNKOWN
Keywords: srs,spaced-repetition
Author: Pacharapol Withayasakpunt
Author-email: patarapolw@gmail.com
Classifier: Programming Language :: Python :: 2
Classifier: Programming Language :: Python :: 2.7
Classifier: Programming Language :: Python :: 3
Classifier: Programming Language :: Python :: 3.4
Classifier: Programming Language :: Python :: 3.5
Classifier: Programming Language :: Python :: 3.6
Classifier: Programming Language :: Python :: 3.7
Requires-Dist: peewee (>=3.7,<4.0)
